{"migrationVersion":{"dashboard":"7.9.3"},"references":[{"type":"visualization","name":"panel_0","id":"dd9b8e50-cb33-11e8-8e2b-bf314673d4bf"},{"type":"visualization","name":"panel_1","id":"837522f0-cb34-11e8-8e2b-bf314673d4bf"},{"type":"visualization","name":"panel_2","id":"48baf4f0-cb34-11e8-8e2b-bf314673d4bf"},{"type":"visualization","name":"panel_3","id":"a6376820-cb3e-11e8-8e2b-bf314673d4bf"},{"type":"visualization","name":"panel_4","id":"eef848e0-cb3e-11e8-8e2b-bf314673d4bf"},{"type":"visualization","name":"panel_5","id":"305b0610-cb3f-11e8-8e2b-bf314673d4bf"},{"type":"visualization","name":"panel_6","id":"04e4ecd0-cb3f-11e8-8e2b-bf314673d4bf"},{"type":"visualization","name":"panel_7","id":"54cb1bf0-cb41-11e8-8e2b-bf314673d4bf"},{"type":"visualization","name":"panel_8","id":"66130c70-cb40-11e8-8e2b-bf314673d4bf"},{"type":"visualization","name":"panel_9","id":"ede2f660-cb40-11e8-8e2b-bf314673d4bf"},{"type":"visualization","name":"panel_10","id":"9ec0d330-cb41-11e8-8e2b-bf314673d4bf"},{"type":"visualization","name":"panel_11","id":"0a54ea10-cb41-11e8-8e2b-bf314673d4bf"},{"type":"visualization","name":"panel_12","id":"a1aa05e0-cb40-11e8-8e2b-bf314673d4bf"},{"type":"search","name":"panel_13","id":"445dee50-cb32-11e8-8e2b-bf314673d4bf"}],"type":"dashboard","dashboard":{"hits":0,"timeFrom":"now-24h","timeRestore":true,"description":"","title":"SN-NFS","panelsJSON":"[{\"embeddableConfig\":{},\"gridData\":{\"x\":0,\"y\":0,\"w\":48,\"h\":9,\"i\":\"1\"},\"panelIndex\":\"1\",\"version\":\"7.3.0\",\"panelRefName\":\"panel_0\"},{\"embeddableConfig\":{},\"gridData\":{\"x\":0,\"y\":9,\"w\":13,\"h\":15,\"i\":\"2\"},\"panelIndex\":\"2\",\"version\":\"7.3.0\",\"panelRefName\":\"panel_1\"},{\"embeddableConfig\":{},\"gridData\":{\"x\":13,\"y\":9,\"w\":35,\"h\":15,\"i\":\"3\"},\"panelIndex\":\"3\",\"version\":\"7.3.0\",\"panelRefName\":\"panel_2\"},{\"embeddableConfig\":{},\"gridData\":{\"x\":0,\"y\":24,\"w\":13,\"h\":16,\"i\":\"4\"},\"panelIndex\":\"4\",\"version\":\"7.3.0\",\"panelRefName\":\"panel_3\"},{\"embeddableConfig\":{},\"gridData\":{\"x\":23,\"y\":24,\"w\":14,\"h\":16,\"i\":\"5\"},\"panelIndex\":\"5\",\"version\":\"7.3.0\",\"panelRefName\":\"panel_4\"},{\"embeddableConfig\":{},\"gridData\":{\"x\":37,\"y\":24,\"w\":11,\"h\":16,\"i\":\"6\"},\"panelIndex\":\"6\",\"version\":\"7.3.0\",\"panelRefName\":\"panel_5\"},{\"embeddableConfig\":{},\"gridData\":{\"x\":13,\"y\":24,\"w\":10,\"h\":16,\"i\":\"7\"},\"panelIndex\":\"7\",\"version\":\"7.3.0\",\"panelRefName\":\"panel_6\"},{\"embeddableConfig\":{},\"gridData\":{\"x\":16,\"y\":40,\"w\":16,\"h\":15,\"i\":\"8\"},\"panelIndex\":\"8\",\"version\":\"7.3.0\",\"panelRefName\":\"panel_7\"},{\"embeddableConfig\":{},\"gridData\":{\"x\":0,\"y\":40,\"w\":16,\"h\":15,\"i\":\"9\"},\"panelIndex\":\"9\",\"version\":\"7.3.0\",\"panelRefName\":\"panel_8\"},{\"embeddableConfig\":{},\"gridData\":{\"x\":16,\"y\":55,\"w\":16,\"h\":15,\"i\":\"10\"},\"panelIndex\":\"10\",\"version\":\"7.3.0\",\"panelRefName\":\"panel_9\"},{\"embeddableConfig\":{},\"gridData\":{\"x\":32,\"y\":40,\"w\":16,\"h\":15,\"i\":\"11\"},\"panelIndex\":\"11\",\"version\":\"7.3.0\",\"panelRefName\":\"panel_10\"},{\"embeddableConfig\":{},\"gridData\":{\"x\":32,\"y\":55,\"w\":16,\"h\":15,\"i\":\"12\"},\"panelIndex\":\"12\",\"version\":\"7.3.0\",\"panelRefName\":\"panel_11\"},{\"embeddableConfig\":{},\"gridData\":{\"x\":0,\"y\":55,\"w\":16,\"h\":15,\"i\":\"13\"},\"panelIndex\":\"13\",\"version\":\"7.3.0\",\"panelRefName\":\"panel_12\"},{\"embeddableConfig\":{},\"gridData\":{\"x\":0,\"y\":70,\"w\":48,\"h\":20,\"i\":\"14\"},\"panelIndex\":\"14\",\"version\":\"7.3.0\",\"panelRefName\":\"panel_13\"}]","timeTo":"now","optionsJSON":"{\"darkTheme\":false,\"hidePanelTitles\":false,\"useMargins\":true}","version":1,"refreshInterval":{"pause":true,"value":0},"kibanaSavedObjectMeta":{"searchSourceJSON":"{\"query\":{\"language\":\"lucene\",\"query\":\"\"},\"filter\":[]}"}},"updated_at":"2018-10-08T21:41:45.649Z"}