{"dashboard":{"description":"","hits":0,"kibanaSavedObjectMeta":{"searchSourceJSON":"{\"query\":{\"language\":\"lucene\",\"query\":\"\"},\"filter\":[]}"},"optionsJSON":"{\"darkTheme\":false,\"hidePanelTitles\":false,\"useMargins\":true}","panelsJSON":"[{\"version\":\"7.3.0\",\"type\":\"visualization\",\"gridData\":{\"h\":12,\"i\":\"1\",\"w\":48,\"x\":0,\"y\":0},\"panelIndex\":\"1\",\"embeddableConfig\":{\"enhancements\":{}},\"panelRefName\":\"panel_1\"},{\"version\":\"7.3.0\",\"type\":\"visualization\",\"gridData\":{\"h\":15,\"i\":\"2\",\"w\":24,\"x\":24,\"y\":12},\"panelIndex\":\"2\",\"embeddableConfig\":{\"enhancements\":{}},\"panelRefName\":\"panel_2\"},{\"version\":\"7.3.0\",\"type\":\"visualization\",\"gridData\":{\"h\":15,\"i\":\"3\",\"w\":24,\"x\":0,\"y\":12},\"panelIndex\":\"3\",\"embeddableConfig\":{\"enhancements\":{}},\"panelRefName\":\"panel_3\"},{\"version\":\"7.3.0\",\"type\":\"visualization\",\"gridData\":{\"h\":13,\"i\":\"4\",\"w\":48,\"x\":0,\"y\":27},\"panelIndex\":\"4\",\"embeddableConfig\":{\"enhancements\":{}},\"panelRefName\":\"panel_4\"}]","refreshInterval":{"pause":true,"value":0},"timeFrom":"now-24h","timeRestore":true,"timeTo":"now","title":"SN-TrafficID","version":1},"type":"dashboard","references":[{"name":"1:panel_1","type":"visualization","id":"1af05bf0-cc06-11e8-aae9-99442e2ed6cc"},{"name":"2:panel_2","type":"visualization","id":"eb100030-cc04-11e8-aae9-99442e2ed6cc"},{"name":"3:panel_3","type":"visualization","id":"d39f5450-cc04-11e8-aae9-99442e2ed6cc"},{"name":"4:panel_4","type":"visualization","id":"3339b490-cc06-11e8-aae9-99442e2ed6cc"}],"migrationVersion":{"dashboard":"7.15.0"},"coreMigrationVersion":"7.15.2","updated_at":"2021-07-30T16:40:32.145Z"}