{"migrationVersion":{"search":"7.9.3"},"references":[{"type":"index-pattern","name":"kibanaSavedObjectMeta.searchSourceJSON.index","id":"logstash-smtp-*"}],"search":{"sort":[["@timestamp","desc"]],"hits":0,"description":"","title":"SN-SMTP-EventsList","version":1,"kibanaSavedObjectMeta":{"searchSourceJSON":"{\"filter\":[],\"highlight\":{\"pre_tags\":[\"@kibana-highlighted-field@\"],\"post_tags\":[\"@/kibana-highlighted-field@\"],\"fields\":{\"*\":{}},\"require_field_match\":false,\"fragment_size\":2147483647},\"query\":{\"query\":{\"query_string\":{\"query\":\"*\",\"analyze_wildcard\":true,\"default_field\":\"*\"}},\"language\":\"lucene\"},\"highlightAll\":true,\"version\":true,\"indexRefName\":\"kibanaSavedObjectMeta.searchSourceJSON.index\"}"},"columns":["EveBox","FPC","src_ip","src_port","proto","dest_ip","dest_port","email.user_agent","email.attachment","email.x_originating_ip"]},"type":"search","updated_at":"2018-10-12T11:58:40.943Z"}